README
fibonacci_heap_mod.py
setup.py
fibonacci_heap_mod.egg-info/PKG-INFO
fibonacci_heap_mod.egg-info/SOURCES.txt
fibonacci_heap_mod.egg-info/dependency_links.txt
fibonacci_heap_mod.egg-info/top_level.txt