Metadata-Version: 1.1
Name: fibonacci-heap-mod
Version: 1.2
Summary: Pure Python Fibonacci Heap (Priority Queue)
Home-page: http://stromberg.dnsalias.org/~strombrg/fibonacci-heap-mod/
Author: Daniel Richard Stromberg
Author-email: strombrg@gmail.com
License: Apache v2
Keywords: Fibonacci Heap,Priority Queue
Platform: Cross platform
Classifier: Development Status :: 5 - Production/Stable
Classifier: Intended Audience :: Developers
Classifier: Programming Language :: Python :: 2
Classifier: Programming Language :: Python :: 3
